[
  {
    "username": "mu venu",
    "password": "$2b$10$qPOZwcf17Vd7OVwxHpkdY.Fp/RgZcFXOxwBCMPtnRbDk.kudn3sJa"
  },
  {
    "username": "nishi",
    "password": "$2b$10$Olwx0g1kuP9o9Worw0tbh.C5KccwwMsZuGGpM.xinfICRefHyUlTO"
  },
  {
    "username": "Venu",
    "password": "$2b$10$Y0WeYM83eRGIRvZY2v9Xt.pesD5yf480iY5EmckumybQky.QXtFyy"
  },
  {
    "username": "poorni",
    "password": "$2b$10$HpXLLPCnY.gIOzove1wWPeh42HYT2ctdIJ3XCkO5Zo4rOgWQ1zAcS"
  },
  {
    "username": "nishika",
    "password": "$2b$10$MPhzkr3aDyLtb3D69retg.CUEmFAvUsqvNpX.0Dwy//DT5l3pvoaS"
  },
  {
    "username": "tamil",
    "password": "$2b$10$XpExILpkFYh3MuQHyxNAN.iNzv4xUTY1efLHuLDQYxCigNIvAOQp6"
  }
]